[{"source":"John Means","target":"John Means","distance":0},{"source":"Jordan Zimmermann","target":"John Means","distance":0.4158},{"source":"Jeff Samardzija","target":"John Means","distance":0.4315},{"source":"Masahiro Tanaka","target":"John Means","distance":0.5058},{"source":"Pablo Lopez","target":"John Means","distance":0.6408},{"source":"Ivan Nova","target":"John Means","distance":0.6508},{"source":"Mike Fiers","target":"John Means","distance":0.6653},{"source":"Cal Quantrill","target":"John Means","distance":0.6902},{"source":"Rick Porcello","target":"John Means","distance":0.7088},{"source":"Zach Eflin","target":"John Means","distance":0.7119},{"source":"Yonny Chirinos","target":"John Means","distance":0.757},{"source":"Miles Mikolas","target":"John Means","distance":0.7749},{"source":"Marco Gonzales","target":"John Means","distance":0.7779},{"source":"Daniel Norris","target":"John Means","distance":0.8318},{"source":"Jose Quintana","target":"John Means","distance":0.8471},{"source":"Jose Urena","target":"John Means","distance":0.8885},{"source":"Trevor Williams","target":"John Means","distance":1.0198},{"source":"Joe Musgrove","target":"John Means","distance":1.0399},{"source":"Merrill Kelly","target":"John Means","distance":1.0703},{"source":"Adam Plutko","target":"John Means","distance":1.101},{"source":"Zach Davies","target":"John Means","distance":1.1301},{"source":"Kyle Hendricks","target":"John Means","distance":1.1368},{"source":"Michael Pineda","target":"John Means","distance":1.2282},{"source":"Jose Berrios","target":"John Means","distance":1.2307},{"source":"Madison Bumgarner","target":"John Means","distance":1.2447},{"source":"Ariel Jurado","target":"John Means","distance":1.2778},{"source":"Zach Plesac","target":"John Means","distance":1.2914},{"source":"Mike Montgomery","target":"John Means","distance":1.2965},{"source":"Mike Soroka","target":"John Means","distance":1.3011},{"source":"Dallas Keuchel","target":"John Means","distance":1.3224},{"source":"Brett Anderson","target":"John Means","distance":1.3438},{"source":"Jon Lester","target":"John Means","distance":1.3449},{"source":"Anibal Sanchez","target":"John Means","distance":1.375},{"source":"Homer Bailey","target":"John Means","distance":1.3791},{"source":"Clay Buchholz","target":"John Means","distance":1.3837},{"source":"Dario Agrazal","target":"John Means","distance":1.3932},{"source":"Tanner Roark","target":"John Means","distance":1.4074},{"source":"Marcus Stroman","target":"John Means","distance":1.4266},{"source":"German Marquez","target":"John Means","distance":1.4268},{"source":"Ross Stripling","target":"John Means","distance":1.4389},{"source":"Chris Bassitt","target":"John Means","distance":1.4494},{"source":"Zack Wheeler","target":"John Means","distance":1.46},{"source":"Andrew Cashner","target":"John Means","distance":1.4825},{"source":"Mike Foltynewicz","target":"John Means","distance":1.4904},{"source":"Brad Peacock","target":"John Means","distance":1.5014},{"source":"Noah Syndergaard","target":"John Means","distance":1.5018},{"source":"Mike Minor","target":"John Means","distance":1.513},{"source":"Chase Anderson","target":"John Means","distance":1.5182},{"source":"Danny Duffy","target":"John Means","distance":1.5258},{"source":"Tyler Mahle","target":"John Means","distance":1.5274},{"source":"Anthony DeSclafani","target":"John Means","distance":1.5345},{"source":"Martin Perez","target":"John Means","distance":1.5445},{"source":"Aaron Civale","target":"John Means","distance":1.5464},{"source":"Jakob Junis","target":"John Means","distance":1.5475},{"source":"Steven Matz","target":"John Means","distance":1.558},{"source":"Eric Lauer","target":"John Means","distance":1.5581},{"source":"Ryan Yarbrough","target":"John Means","distance":1.5584},{"source":"Yusei Kikuchi","target":"John Means","distance":1.5604},{"source":"Wade Miley","target":"John Means","distance":1.5691},{"source":"J.A. Happ","target":"John Means","distance":1.5941},{"source":"Clayton Kershaw","target":"John Means","distance":1.598},{"source":"Aaron Brooks","target":"John Means","distance":1.6042},{"source":"Zack Greinke","target":"John Means","distance":1.6054},{"source":"Max Fried","target":"John Means","distance":1.619},{"source":"Shaun Anderson","target":"John Means","distance":1.6368},{"source":"Mike Leake","target":"John Means","distance":1.6415},{"source":"Alex Young","target":"John Means","distance":1.6491},{"source":"Jake Arrieta","target":"John Means","distance":1.6493},{"source":"Joey Lucchesi","target":"John Means","distance":1.6659},{"source":"Nick Margevicius","target":"John Means","distance":1.6756},{"source":"Jacob Waguespack","target":"John Means","distance":1.6989},{"source":"Kyle Gibson","target":"John Means","distance":1.7186},{"source":"Chris Paddack","target":"John Means","distance":1.7548},{"source":"Hyun-Jin Ryu","target":"John Means","distance":1.7711},{"source":"Reynaldo Lopez","target":"John Means","distance":1.7799},{"source":"Adrian Houser","target":"John Means","distance":1.7897},{"source":"Adam Wainwright","target":"John Means","distance":1.7938},{"source":"Glenn Sparkman","target":"John Means","distance":1.852},{"source":"Tyler Skaggs","target":"John Means","distance":1.89},{"source":"Tyler Beede","target":"John Means","distance":1.8981},{"source":"Griffin Canning","target":"John Means","distance":1.9204},{"source":"Kevin Gausman","target":"John Means","distance":1.922},{"source":"Jon Gray","target":"John Means","distance":1.926},{"source":"Luke Weaver","target":"John Means","distance":1.9416},{"source":"Asher Wojciechowski","target":"John Means","distance":1.9491},{"source":"Matt Strahm","target":"John Means","distance":1.9898},{"source":"Dylan Bundy","target":"John Means","distance":1.9961},{"source":"Frankie Montas","target":"John Means","distance":2.0315},{"source":"Felix Hernandez","target":"John Means","distance":2.0643},{"source":"Kenta Maeda","target":"John Means","distance":2.0667},{"source":"Domingo German","target":"John Means","distance":2.089},{"source":"Sandy Alcantara","target":"John Means","distance":2.0911},{"source":"Dereck Rodriguez","target":"John Means","distance":2.1231},{"source":"Nick Pivetta","target":"John Means","distance":2.15},{"source":"Elieser Hernandez","target":"John Means","distance":2.1774},{"source":"Peter Lambert","target":"John Means","distance":2.1926},{"source":"Jason Vargas","target":"John Means","distance":2.2214},{"source":"Eduardo Rodriguez","target":"John Means","distance":2.2306},{"source":"Jack Flaherty","target":"John Means","distance":2.2429},{"source":"Jorge Lopez","target":"John Means","distance":2.2505},{"source":"Trevor Richards","target":"John Means","distance":2.2597},{"source":"Kyle Freeland","target":"John Means","distance":2.2785},{"source":"Walker Buehler","target":"John Means","distance":2.3114},{"source":"Cole Hamels","target":"John Means","distance":2.3306},{"source":"Brandon Woodruff","target":"John Means","distance":2.3331},{"source":"Erick Fedde","target":"John Means","distance":2.3355},{"source":"David Price","target":"John Means","distance":2.3428},{"source":"Jake Odorizzi","target":"John Means","distance":2.3471},{"source":"Jordan Lyles","target":"John Means","distance":2.3586},{"source":"Stephen Strasburg","target":"John Means","distance":2.3828},{"source":"Shane Bieber","target":"John Means","distance":2.3867},{"source":"Vince Velasquez","target":"John Means","distance":2.3907},{"source":"Brad Keller","target":"John Means","distance":2.3958},{"source":"Lance Lynn","target":"John Means","distance":2.4},{"source":"Taylor Clarke","target":"John Means","distance":2.4108},{"source":"Adrian Sampson","target":"John Means","distance":2.4319},{"source":"Spencer Turnbull","target":"John Means","distance":2.4319},{"source":"Trent Thornton","target":"John Means","distance":2.4612},{"source":"Steven Brault","target":"John Means","distance":2.4849},{"source":"Patrick Corbin","target":"John Means","distance":2.5619},{"source":"Rich Hill","target":"John Means","distance":2.562},{"source":"Gio Gonzalez","target":"John Means","distance":2.5932},{"source":"Michael Wacha","target":"John Means","distance":2.5946},{"source":"Antonio Senzatela","target":"John Means","distance":2.6158},{"source":"Aaron Nola","target":"John Means","distance":2.6842},{"source":"Ross Detwiler","target":"John Means","distance":2.7034},{"source":"Jacob deGrom","target":"John Means","distance":2.716},{"source":"CC Sabathia","target":"John Means","distance":2.7189},{"source":"Dillon Peters","target":"John Means","distance":2.7512},{"source":"Carlos Carrasco","target":"John Means","distance":2.7531},{"source":"Caleb Smith","target":"John Means","distance":2.7789},{"source":"Trevor Bauer","target":"John Means","distance":2.7981},{"source":"Charlie Morton","target":"John Means","distance":2.8316},{"source":"Andrew Heaney","target":"John Means","distance":2.832},{"source":"James Paxton","target":"John Means","distance":2.8541},{"source":"Yu Darvish","target":"John Means","distance":2.8813},{"source":"Lucas Giolito","target":"John Means","distance":2.8939},{"source":"Sonny Gray","target":"John Means","distance":2.9002},{"source":"Jerad Eickhoff","target":"John Means","distance":2.9156},{"source":"Matthew Boyd","target":"John Means","distance":2.9206},{"source":"Tyler Glasnow","target":"John Means","distance":2.9364},{"source":"Julio Teheran","target":"John Means","distance":2.9523},{"source":"Dakota Hudson","target":"John Means","distance":2.9566},{"source":"Jordan Yamamoto","target":"John Means","distance":2.9708},{"source":"Trevor Cahill","target":"John Means","distance":2.9815},{"source":"Justin Verlander","target":"John Means","distance":3.038},{"source":"Luis Castillo","target":"John Means","distance":3.0683},{"source":"Jose Suarez","target":"John Means","distance":3.0871},{"source":"Matt Harvey","target":"John Means","distance":3.1613},{"source":"Jhoulys Chacin","target":"John Means","distance":3.1638},{"source":"Gabriel Ynoa","target":"John Means","distance":3.1973},{"source":"Jaime Barria","target":"John Means","distance":3.2531},{"source":"Mike Clevinger","target":"John Means","distance":3.2767},{"source":"Aaron Sanchez","target":"John Means","distance":3.3292},{"source":"Max Scherzer","target":"John Means","distance":3.4287},{"source":"Zac Gallen","target":"John Means","distance":3.466},{"source":"Chi Chi Gonzalez","target":"John Means","distance":3.4959},{"source":"Blake Snell","target":"John Means","distance":3.5025},{"source":"Dylan Cease","target":"John Means","distance":3.5113},{"source":"Chris Archer","target":"John Means","distance":3.5876},{"source":"Drew Smyly","target":"John Means","distance":3.6056},{"source":"Chris Sale","target":"John Means","distance":3.6424},{"source":"Edwin Jackson","target":"John Means","distance":3.6763},{"source":"Drew Pomeranz","target":"John Means","distance":3.8221},{"source":"Gerrit Cole","target":"John Means","distance":3.9086},{"source":"Dinelson Lamet","target":"John Means","distance":3.9882},{"source":"David Hess","target":"John Means","distance":4.054},{"source":"Jeff Hoffman","target":"John Means","distance":4.129},{"source":"Robbie Ray","target":"John Means","distance":4.1448},{"source":"Nathan Eovaldi","target":"John Means","distance":4.6164}]
