[{"source":"Luke Weaver","target":"Luke Weaver","distance":0},{"source":"Frankie Montas","target":"Luke Weaver","distance":0.3151},{"source":"Brandon Woodruff","target":"Luke Weaver","distance":0.6125},{"source":"Walker Buehler","target":"Luke Weaver","distance":0.6223},{"source":"Zack Wheeler","target":"Luke Weaver","distance":0.6631},{"source":"Noah Syndergaard","target":"Luke Weaver","distance":0.6931},{"source":"Jacob deGrom","target":"Luke Weaver","distance":0.8646},{"source":"Joe Musgrove","target":"Luke Weaver","distance":0.9181},{"source":"Jose Berrios","target":"Luke Weaver","distance":0.9215},{"source":"Stephen Strasburg","target":"Luke Weaver","distance":0.9356},{"source":"Lance Lynn","target":"Luke Weaver","distance":0.9386},{"source":"Max Fried","target":"Luke Weaver","distance":0.9547},{"source":"Ross Stripling","target":"Luke Weaver","distance":0.9659},{"source":"Tyler Glasnow","target":"Luke Weaver","distance":1.0199},{"source":"Madison Bumgarner","target":"Luke Weaver","distance":1.0369},{"source":"Jack Flaherty","target":"Luke Weaver","distance":1.08},{"source":"Clayton Kershaw","target":"Luke Weaver","distance":1.1727},{"source":"Kyle Hendricks","target":"Luke Weaver","distance":1.2},{"source":"Shane Bieber","target":"Luke Weaver","distance":1.2027},{"source":"Charlie Morton","target":"Luke Weaver","distance":1.2147},{"source":"Jose Quintana","target":"Luke Weaver","distance":1.2204},{"source":"Zack Greinke","target":"Luke Weaver","distance":1.2237},{"source":"Chris Paddack","target":"Luke Weaver","distance":1.2635},{"source":"Mike Soroka","target":"Luke Weaver","distance":1.2958},{"source":"Michael Pineda","target":"Luke Weaver","distance":1.3189},{"source":"Pablo Lopez","target":"Luke Weaver","distance":1.3272},{"source":"Hyun-Jin Ryu","target":"Luke Weaver","distance":1.3347},{"source":"Jake Odorizzi","target":"Luke Weaver","distance":1.3709},{"source":"German Marquez","target":"Luke Weaver","distance":1.374},{"source":"David Price","target":"Luke Weaver","distance":1.3829},{"source":"Yonny Chirinos","target":"Luke Weaver","distance":1.422},{"source":"Brad Peacock","target":"Luke Weaver","distance":1.4781},{"source":"Marcus Stroman","target":"Luke Weaver","distance":1.5206},{"source":"Jon Lester","target":"Luke Weaver","distance":1.5378},{"source":"Aaron Civale","target":"Luke Weaver","distance":1.5687},{"source":"Adrian Houser","target":"Luke Weaver","distance":1.581},{"source":"Ryan Yarbrough","target":"Luke Weaver","distance":1.5863},{"source":"Daniel Norris","target":"Luke Weaver","distance":1.5941},{"source":"Mike Clevinger","target":"Luke Weaver","distance":1.5964},{"source":"Homer Bailey","target":"Luke Weaver","distance":1.5981},{"source":"Griffin Canning","target":"Luke Weaver","distance":1.6002},{"source":"Patrick Corbin","target":"Luke Weaver","distance":1.6498},{"source":"Tyler Skaggs","target":"Luke Weaver","distance":1.6552},{"source":"Mike Minor","target":"Luke Weaver","distance":1.6579},{"source":"Masahiro Tanaka","target":"Luke Weaver","distance":1.6709},{"source":"Kenta Maeda","target":"Luke Weaver","distance":1.6749},{"source":"Max Scherzer","target":"Luke Weaver","distance":1.683},{"source":"Chris Bassitt","target":"Luke Weaver","distance":1.7155},{"source":"Jon Gray","target":"Luke Weaver","distance":1.7327},{"source":"Cal Quantrill","target":"Luke Weaver","distance":1.7357},{"source":"Anthony DeSclafani","target":"Luke Weaver","distance":1.7452},{"source":"Kyle Gibson","target":"Luke Weaver","distance":1.7497},{"source":"Kevin Gausman","target":"Luke Weaver","distance":1.7513},{"source":"Joey Lucchesi","target":"Luke Weaver","distance":1.7521},{"source":"Miles Mikolas","target":"Luke Weaver","distance":1.7789},{"source":"Lucas Giolito","target":"Luke Weaver","distance":1.7849},{"source":"Eric Lauer","target":"Luke Weaver","distance":1.79},{"source":"Eduardo Rodriguez","target":"Luke Weaver","distance":1.8155},{"source":"Tanner Roark","target":"Luke Weaver","distance":1.8157},{"source":"Justin Verlander","target":"Luke Weaver","distance":1.8355},{"source":"Marco Gonzales","target":"Luke Weaver","distance":1.8546},{"source":"Rich Hill","target":"Luke Weaver","distance":1.8835},{"source":"Merrill Kelly","target":"Luke Weaver","distance":1.8889},{"source":"Tyler Mahle","target":"Luke Weaver","distance":1.9119},{"source":"Jeff Samardzija","target":"Luke Weaver","distance":1.9255},{"source":"John Means","target":"Luke Weaver","distance":1.9416},{"source":"Steven Matz","target":"Luke Weaver","distance":1.9515},{"source":"Rick Porcello","target":"Luke Weaver","distance":2.0084},{"source":"Sonny Gray","target":"Luke Weaver","distance":2.0329},{"source":"Jakob Junis","target":"Luke Weaver","distance":2.1052},{"source":"Adam Wainwright","target":"Luke Weaver","distance":2.1053},{"source":"Anibal Sanchez","target":"Luke Weaver","distance":2.1138},{"source":"Spencer Turnbull","target":"Luke Weaver","distance":2.1364},{"source":"Cole Hamels","target":"Luke Weaver","distance":2.1447},{"source":"Jordan Zimmermann","target":"Luke Weaver","distance":2.1549},{"source":"Dallas Keuchel","target":"Luke Weaver","distance":2.1621},{"source":"Zach Eflin","target":"Luke Weaver","distance":2.1669},{"source":"James Paxton","target":"Luke Weaver","distance":2.1681},{"source":"Danny Duffy","target":"Luke Weaver","distance":2.1928},{"source":"Wade Miley","target":"Luke Weaver","distance":2.2048},{"source":"Aaron Nola","target":"Luke Weaver","distance":2.2087},{"source":"Chase Anderson","target":"Luke Weaver","distance":2.2202},{"source":"Yu Darvish","target":"Luke Weaver","distance":2.2295},{"source":"Dylan Bundy","target":"Luke Weaver","distance":2.2768},{"source":"Jose Urena","target":"Luke Weaver","distance":2.2843},{"source":"Mike Foltynewicz","target":"Luke Weaver","distance":2.3466},{"source":"Trevor Bauer","target":"Luke Weaver","distance":2.3483},{"source":"Carlos Carrasco","target":"Luke Weaver","distance":2.3783},{"source":"Chris Sale","target":"Luke Weaver","distance":2.3812},{"source":"Gerrit Cole","target":"Luke Weaver","distance":2.3855},{"source":"Luis Castillo","target":"Luke Weaver","distance":2.3863},{"source":"Alex Young","target":"Luke Weaver","distance":2.3887},{"source":"Mike Fiers","target":"Luke Weaver","distance":2.4034},{"source":"Trevor Williams","target":"Luke Weaver","distance":2.4092},{"source":"Domingo German","target":"Luke Weaver","distance":2.4151},{"source":"Matthew Boyd","target":"Luke Weaver","distance":2.4187},{"source":"Blake Snell","target":"Luke Weaver","distance":2.4245},{"source":"Martin Perez","target":"Luke Weaver","distance":2.4461},{"source":"Reynaldo Lopez","target":"Luke Weaver","distance":2.4643},{"source":"Zach Plesac","target":"Luke Weaver","distance":2.4772},{"source":"Zach Davies","target":"Luke Weaver","distance":2.4813},{"source":"Jake Arrieta","target":"Luke Weaver","distance":2.4879},{"source":"Mike Montgomery","target":"Luke Weaver","distance":2.515},{"source":"Andrew Heaney","target":"Luke Weaver","distance":2.5156},{"source":"Jordan Lyles","target":"Luke Weaver","distance":2.5213},{"source":"Tyler Beede","target":"Luke Weaver","distance":2.5227},{"source":"Matt Strahm","target":"Luke Weaver","distance":2.5347},{"source":"Trevor Richards","target":"Luke Weaver","distance":2.5534},{"source":"Jacob Waguespack","target":"Luke Weaver","distance":2.5535},{"source":"Ivan Nova","target":"Luke Weaver","distance":2.5771},{"source":"Elieser Hernandez","target":"Luke Weaver","distance":2.5843},{"source":"Asher Wojciechowski","target":"Luke Weaver","distance":2.5892},{"source":"Vince Velasquez","target":"Luke Weaver","distance":2.6397},{"source":"Andrew Cashner","target":"Luke Weaver","distance":2.6746},{"source":"Adam Plutko","target":"Luke Weaver","distance":2.675},{"source":"J.A. Happ","target":"Luke Weaver","distance":2.6818},{"source":"Sandy Alcantara","target":"Luke Weaver","distance":2.7195},{"source":"Ariel Jurado","target":"Luke Weaver","distance":2.745},{"source":"Trent Thornton","target":"Luke Weaver","distance":2.7675},{"source":"Jason Vargas","target":"Luke Weaver","distance":2.7703},{"source":"Zac Gallen","target":"Luke Weaver","distance":2.7736},{"source":"Steven Brault","target":"Luke Weaver","distance":2.8107},{"source":"Gio Gonzalez","target":"Luke Weaver","distance":2.8203},{"source":"Brett Anderson","target":"Luke Weaver","distance":2.8417},{"source":"Shaun Anderson","target":"Luke Weaver","distance":2.8565},{"source":"Brad Keller","target":"Luke Weaver","distance":2.8912},{"source":"Jordan Yamamoto","target":"Luke Weaver","distance":2.9185},{"source":"Caleb Smith","target":"Luke Weaver","distance":2.9872},{"source":"Aaron Brooks","target":"Luke Weaver","distance":3.0396},{"source":"Mike Leake","target":"Luke Weaver","distance":3.0764},{"source":"Yusei Kikuchi","target":"Luke Weaver","distance":3.0794},{"source":"Clay Buchholz","target":"Luke Weaver","distance":3.096},{"source":"Julio Teheran","target":"Luke Weaver","distance":3.1331},{"source":"Dinelson Lamet","target":"Luke Weaver","distance":3.1421},{"source":"Nick Margevicius","target":"Luke Weaver","distance":3.181},{"source":"Nick Pivetta","target":"Luke Weaver","distance":3.2161},{"source":"Dario Agrazal","target":"Luke Weaver","distance":3.2789},{"source":"Felix Hernandez","target":"Luke Weaver","distance":3.2864},{"source":"Jorge Lopez","target":"Luke Weaver","distance":3.3869},{"source":"CC Sabathia","target":"Luke Weaver","distance":3.4043},{"source":"Michael Wacha","target":"Luke Weaver","distance":3.4735},{"source":"Dereck Rodriguez","target":"Luke Weaver","distance":3.4957},{"source":"Dakota Hudson","target":"Luke Weaver","distance":3.5076},{"source":"Adrian Sampson","target":"Luke Weaver","distance":3.539},{"source":"Kyle Freeland","target":"Luke Weaver","distance":3.5505},{"source":"Chris Archer","target":"Luke Weaver","distance":3.5525},{"source":"Peter Lambert","target":"Luke Weaver","distance":3.5897},{"source":"Glenn Sparkman","target":"Luke Weaver","distance":3.5993},{"source":"Taylor Clarke","target":"Luke Weaver","distance":3.6024},{"source":"Robbie Ray","target":"Luke Weaver","distance":3.6429},{"source":"Dylan Cease","target":"Luke Weaver","distance":3.6632},{"source":"Antonio Senzatela","target":"Luke Weaver","distance":3.7272},{"source":"Aaron Sanchez","target":"Luke Weaver","distance":3.7697},{"source":"Jhoulys Chacin","target":"Luke Weaver","distance":3.7764},{"source":"Erick Fedde","target":"Luke Weaver","distance":3.7822},{"source":"Dillon Peters","target":"Luke Weaver","distance":3.9543},{"source":"Drew Pomeranz","target":"Luke Weaver","distance":4.022},{"source":"Jose Suarez","target":"Luke Weaver","distance":4.0448},{"source":"Drew Smyly","target":"Luke Weaver","distance":4.0499},{"source":"Jerad Eickhoff","target":"Luke Weaver","distance":4.0842},{"source":"Ross Detwiler","target":"Luke Weaver","distance":4.1318},{"source":"Trevor Cahill","target":"Luke Weaver","distance":4.1802},{"source":"Jaime Barria","target":"Luke Weaver","distance":4.1979},{"source":"Matt Harvey","target":"Luke Weaver","distance":4.3438},{"source":"Chi Chi Gonzalez","target":"Luke Weaver","distance":4.4366},{"source":"Edwin Jackson","target":"Luke Weaver","distance":4.7739},{"source":"Jeff Hoffman","target":"Luke Weaver","distance":4.8784},{"source":"Gabriel Ynoa","target":"Luke Weaver","distance":4.9081},{"source":"David Hess","target":"Luke Weaver","distance":5.1339},{"source":"Nathan Eovaldi","target":"Luke Weaver","distance":5.279}]
