[{"source":"Patrick Corbin","target":"Patrick Corbin","distance":0},{"source":"Jake Odorizzi","target":"Patrick Corbin","distance":0.4533},{"source":"Kenta Maeda","target":"Patrick Corbin","distance":0.6238},{"source":"Sonny Gray","target":"Patrick Corbin","distance":0.625},{"source":"Aaron Nola","target":"Patrick Corbin","distance":0.6633},{"source":"Eduardo Rodriguez","target":"Patrick Corbin","distance":0.6831},{"source":"David Price","target":"Patrick Corbin","distance":0.6876},{"source":"Lucas Giolito","target":"Patrick Corbin","distance":0.6888},{"source":"James Paxton","target":"Patrick Corbin","distance":0.6962},{"source":"Griffin Canning","target":"Patrick Corbin","distance":0.776},{"source":"Luis Castillo","target":"Patrick Corbin","distance":0.7914},{"source":"Jack Flaherty","target":"Patrick Corbin","distance":0.7916},{"source":"Lance Lynn","target":"Patrick Corbin","distance":0.8033},{"source":"Trevor Bauer","target":"Patrick Corbin","distance":0.8625},{"source":"Jon Gray","target":"Patrick Corbin","distance":0.8696},{"source":"Adrian Houser","target":"Patrick Corbin","distance":0.9024},{"source":"Stephen Strasburg","target":"Patrick Corbin","distance":0.9278},{"source":"Kevin Gausman","target":"Patrick Corbin","distance":0.94},{"source":"Tyler Skaggs","target":"Patrick Corbin","distance":0.9734},{"source":"Cole Hamels","target":"Patrick Corbin","distance":0.9988},{"source":"Charlie Morton","target":"Patrick Corbin","distance":1.0179},{"source":"Blake Snell","target":"Patrick Corbin","distance":1.0239},{"source":"Kyle Gibson","target":"Patrick Corbin","distance":1.0407},{"source":"Rich Hill","target":"Patrick Corbin","distance":1.0598},{"source":"Max Fried","target":"Patrick Corbin","distance":1.0739},{"source":"Joey Lucchesi","target":"Patrick Corbin","distance":1.1008},{"source":"Mike Minor","target":"Patrick Corbin","distance":1.1776},{"source":"Spencer Turnbull","target":"Patrick Corbin","distance":1.196},{"source":"Brandon Woodruff","target":"Patrick Corbin","distance":1.2175},{"source":"Mike Clevinger","target":"Patrick Corbin","distance":1.2387},{"source":"Zac Gallen","target":"Patrick Corbin","distance":1.2536},{"source":"Eric Lauer","target":"Patrick Corbin","distance":1.2689},{"source":"Chris Bassitt","target":"Patrick Corbin","distance":1.2793},{"source":"Brad Peacock","target":"Patrick Corbin","distance":1.3027},{"source":"Jon Lester","target":"Patrick Corbin","distance":1.3039},{"source":"Noah Syndergaard","target":"Patrick Corbin","distance":1.3234},{"source":"Homer Bailey","target":"Patrick Corbin","distance":1.3288},{"source":"Yu Darvish","target":"Patrick Corbin","distance":1.3426},{"source":"Jordan Lyles","target":"Patrick Corbin","distance":1.3628},{"source":"Zack Wheeler","target":"Patrick Corbin","distance":1.3794},{"source":"Dylan Bundy","target":"Patrick Corbin","distance":1.3845},{"source":"Steven Matz","target":"Patrick Corbin","distance":1.4222},{"source":"Adam Wainwright","target":"Patrick Corbin","distance":1.4366},{"source":"Anthony DeSclafani","target":"Patrick Corbin","distance":1.4487},{"source":"Tanner Roark","target":"Patrick Corbin","distance":1.4735},{"source":"Jose Berrios","target":"Patrick Corbin","distance":1.4758},{"source":"Frankie Montas","target":"Patrick Corbin","distance":1.4855},{"source":"Jordan Yamamoto","target":"Patrick Corbin","distance":1.4995},{"source":"Trevor Richards","target":"Patrick Corbin","distance":1.5023},{"source":"Jakob Junis","target":"Patrick Corbin","distance":1.582},{"source":"Trent Thornton","target":"Patrick Corbin","distance":1.5915},{"source":"Clayton Kershaw","target":"Patrick Corbin","distance":1.62},{"source":"Marcus Stroman","target":"Patrick Corbin","distance":1.6243},{"source":"Jacob deGrom","target":"Patrick Corbin","distance":1.6309},{"source":"Danny Duffy","target":"Patrick Corbin","distance":1.6365},{"source":"Luke Weaver","target":"Patrick Corbin","distance":1.6498},{"source":"Walker Buehler","target":"Patrick Corbin","distance":1.6745},{"source":"Chase Anderson","target":"Patrick Corbin","distance":1.6841},{"source":"Dinelson Lamet","target":"Patrick Corbin","distance":1.6871},{"source":"Tyler Glasnow","target":"Patrick Corbin","distance":1.6911},{"source":"Wade Miley","target":"Patrick Corbin","distance":1.7054},{"source":"Andrew Heaney","target":"Patrick Corbin","distance":1.7086},{"source":"Chris Paddack","target":"Patrick Corbin","distance":1.7327},{"source":"Merrill Kelly","target":"Patrick Corbin","distance":1.7364},{"source":"Steven Brault","target":"Patrick Corbin","distance":1.7545},{"source":"Alex Young","target":"Patrick Corbin","distance":1.7851},{"source":"Vince Velasquez","target":"Patrick Corbin","distance":1.7932},{"source":"Reynaldo Lopez","target":"Patrick Corbin","distance":1.7975},{"source":"Tyler Beede","target":"Patrick Corbin","distance":1.8005},{"source":"Joe Musgrove","target":"Patrick Corbin","distance":1.8087},{"source":"Anibal Sanchez","target":"Patrick Corbin","distance":1.8148},{"source":"Dallas Keuchel","target":"Patrick Corbin","distance":1.8471},{"source":"Jose Quintana","target":"Patrick Corbin","distance":1.8499},{"source":"Gio Gonzalez","target":"Patrick Corbin","distance":1.8588},{"source":"Caleb Smith","target":"Patrick Corbin","distance":1.8599},{"source":"Tyler Mahle","target":"Patrick Corbin","distance":1.886},{"source":"Shane Bieber","target":"Patrick Corbin","distance":1.9031},{"source":"Daniel Norris","target":"Patrick Corbin","distance":1.9066},{"source":"Jake Arrieta","target":"Patrick Corbin","distance":1.9236},{"source":"Asher Wojciechowski","target":"Patrick Corbin","distance":1.932},{"source":"Ross Stripling","target":"Patrick Corbin","distance":1.9322},{"source":"Julio Teheran","target":"Patrick Corbin","distance":1.9334},{"source":"Matthew Boyd","target":"Patrick Corbin","distance":1.9384},{"source":"Jason Vargas","target":"Patrick Corbin","distance":1.9412},{"source":"Madison Bumgarner","target":"Patrick Corbin","distance":1.9514},{"source":"Mike Foltynewicz","target":"Patrick Corbin","distance":1.9843},{"source":"Martin Perez","target":"Patrick Corbin","distance":1.9985},{"source":"Chris Sale","target":"Patrick Corbin","distance":2.0086},{"source":"Pablo Lopez","target":"Patrick Corbin","distance":2.0103},{"source":"Robbie Ray","target":"Patrick Corbin","distance":2.0226},{"source":"Cal Quantrill","target":"Patrick Corbin","distance":2.0315},{"source":"Jacob Waguespack","target":"Patrick Corbin","distance":2.0742},{"source":"German Marquez","target":"Patrick Corbin","distance":2.0753},{"source":"Chris Archer","target":"Patrick Corbin","distance":2.091},{"source":"Domingo German","target":"Patrick Corbin","distance":2.1284},{"source":"Sandy Alcantara","target":"Patrick Corbin","distance":2.1354},{"source":"Justin Verlander","target":"Patrick Corbin","distance":2.1471},{"source":"Max Scherzer","target":"Patrick Corbin","distance":2.1481},{"source":"Yonny Chirinos","target":"Patrick Corbin","distance":2.1492},{"source":"Elieser Hernandez","target":"Patrick Corbin","distance":2.1533},{"source":"Zach Plesac","target":"Patrick Corbin","distance":2.1855},{"source":"Michael Pineda","target":"Patrick Corbin","distance":2.202},{"source":"Aaron Civale","target":"Patrick Corbin","distance":2.2058},{"source":"Dylan Cease","target":"Patrick Corbin","distance":2.2249},{"source":"Mike Montgomery","target":"Patrick Corbin","distance":2.2407},{"source":"Jeff Samardzija","target":"Patrick Corbin","distance":2.2566},{"source":"Gerrit Cole","target":"Patrick Corbin","distance":2.2608},{"source":"Rick Porcello","target":"Patrick Corbin","distance":2.2845},{"source":"Zach Eflin","target":"Patrick Corbin","distance":2.2925},{"source":"Mike Soroka","target":"Patrick Corbin","distance":2.3093},{"source":"Trevor Williams","target":"Patrick Corbin","distance":2.3522},{"source":"Marco Gonzales","target":"Patrick Corbin","distance":2.356},{"source":"Brad Keller","target":"Patrick Corbin","distance":2.3707},{"source":"Masahiro Tanaka","target":"Patrick Corbin","distance":2.3908},{"source":"J.A. Happ","target":"Patrick Corbin","distance":2.4138},{"source":"Andrew Cashner","target":"Patrick Corbin","distance":2.4319},{"source":"Jose Urena","target":"Patrick Corbin","distance":2.4618},{"source":"Kyle Hendricks","target":"Patrick Corbin","distance":2.514},{"source":"Michael Wacha","target":"Patrick Corbin","distance":2.5369},{"source":"Dakota Hudson","target":"Patrick Corbin","distance":2.5443},{"source":"Aaron Sanchez","target":"Patrick Corbin","distance":2.5453},{"source":"Ariel Jurado","target":"Patrick Corbin","distance":2.5579},{"source":"Shaun Anderson","target":"Patrick Corbin","distance":2.5581},{"source":"John Means","target":"Patrick Corbin","distance":2.5619},{"source":"CC Sabathia","target":"Patrick Corbin","distance":2.6211},{"source":"Nick Pivetta","target":"Patrick Corbin","distance":2.6229},{"source":"Mike Fiers","target":"Patrick Corbin","distance":2.6267},{"source":"Zach Davies","target":"Patrick Corbin","distance":2.6423},{"source":"Drew Pomeranz","target":"Patrick Corbin","distance":2.6477},{"source":"Jhoulys Chacin","target":"Patrick Corbin","distance":2.6752},{"source":"Carlos Carrasco","target":"Patrick Corbin","distance":2.7093},{"source":"Aaron Brooks","target":"Patrick Corbin","distance":2.7424},{"source":"Zack Greinke","target":"Patrick Corbin","distance":2.7498},{"source":"Matt Strahm","target":"Patrick Corbin","distance":2.7551},{"source":"Jordan Zimmermann","target":"Patrick Corbin","distance":2.7561},{"source":"Felix Hernandez","target":"Patrick Corbin","distance":2.8204},{"source":"Miles Mikolas","target":"Patrick Corbin","distance":2.8212},{"source":"Drew Smyly","target":"Patrick Corbin","distance":2.8343},{"source":"Jorge Lopez","target":"Patrick Corbin","distance":2.8343},{"source":"Hyun-Jin Ryu","target":"Patrick Corbin","distance":2.9021},{"source":"Yusei Kikuchi","target":"Patrick Corbin","distance":2.9426},{"source":"Adam Plutko","target":"Patrick Corbin","distance":2.981},{"source":"Nick Margevicius","target":"Patrick Corbin","distance":2.9864},{"source":"Kyle Freeland","target":"Patrick Corbin","distance":3.0078},{"source":"Taylor Clarke","target":"Patrick Corbin","distance":3.0155},{"source":"Dereck Rodriguez","target":"Patrick Corbin","distance":3.0254},{"source":"Ryan Yarbrough","target":"Patrick Corbin","distance":3.0574},{"source":"Ivan Nova","target":"Patrick Corbin","distance":3.0662},{"source":"Peter Lambert","target":"Patrick Corbin","distance":3.0853},{"source":"Antonio Senzatela","target":"Patrick Corbin","distance":3.1008},{"source":"Clay Buchholz","target":"Patrick Corbin","distance":3.2246},{"source":"Dillon Peters","target":"Patrick Corbin","distance":3.2418},{"source":"Jose Suarez","target":"Patrick Corbin","distance":3.2994},{"source":"Brett Anderson","target":"Patrick Corbin","distance":3.3368},{"source":"Erick Fedde","target":"Patrick Corbin","distance":3.4295},{"source":"Chi Chi Gonzalez","target":"Patrick Corbin","distance":3.4837},{"source":"Matt Harvey","target":"Patrick Corbin","distance":3.5046},{"source":"Adrian Sampson","target":"Patrick Corbin","distance":3.5263},{"source":"Dario Agrazal","target":"Patrick Corbin","distance":3.5898},{"source":"Glenn Sparkman","target":"Patrick Corbin","distance":3.6039},{"source":"Ross Detwiler","target":"Patrick Corbin","distance":3.6261},{"source":"Jerad Eickhoff","target":"Patrick Corbin","distance":3.6987},{"source":"Trevor Cahill","target":"Patrick Corbin","distance":3.7296},{"source":"Jaime Barria","target":"Patrick Corbin","distance":3.7453},{"source":"Jeff Hoffman","target":"Patrick Corbin","distance":3.7766},{"source":"Mike Leake","target":"Patrick Corbin","distance":3.9051},{"source":"Edwin Jackson","target":"Patrick Corbin","distance":3.9665},{"source":"Nathan Eovaldi","target":"Patrick Corbin","distance":3.9831},{"source":"David Hess","target":"Patrick Corbin","distance":4.5295},{"source":"Gabriel Ynoa","target":"Patrick Corbin","distance":5.0673}]
