[{"source":"Trevor Cahill","target":"Trevor Cahill","distance":0},{"source":"Jerad Eickhoff","target":"Trevor Cahill","distance":0.2381},{"source":"Jaime Barria","target":"Trevor Cahill","distance":0.6985},{"source":"Jose Suarez","target":"Trevor Cahill","distance":0.7842},{"source":"Taylor Clarke","target":"Trevor Cahill","distance":1.0117},{"source":"Jorge Lopez","target":"Trevor Cahill","distance":1.0526},{"source":"David Hess","target":"Trevor Cahill","distance":1.0777},{"source":"Ross Detwiler","target":"Trevor Cahill","distance":1.0992},{"source":"Edwin Jackson","target":"Trevor Cahill","distance":1.1205},{"source":"Felix Hernandez","target":"Trevor Cahill","distance":1.1495},{"source":"Kyle Freeland","target":"Trevor Cahill","distance":1.1825},{"source":"Adrian Sampson","target":"Trevor Cahill","distance":1.201},{"source":"CC Sabathia","target":"Trevor Cahill","distance":1.2496},{"source":"Nick Pivetta","target":"Trevor Cahill","distance":1.2647},{"source":"Dillon Peters","target":"Trevor Cahill","distance":1.2697},{"source":"Dereck Rodriguez","target":"Trevor Cahill","distance":1.3898},{"source":"Nick Margevicius","target":"Trevor Cahill","distance":1.4344},{"source":"Yusei Kikuchi","target":"Trevor Cahill","distance":1.5042},{"source":"J.A. Happ","target":"Trevor Cahill","distance":1.544},{"source":"Glenn Sparkman","target":"Trevor Cahill","distance":1.625},{"source":"Aaron Brooks","target":"Trevor Cahill","distance":1.7143},{"source":"Clay Buchholz","target":"Trevor Cahill","distance":1.7829},{"source":"Jhoulys Chacin","target":"Trevor Cahill","distance":1.7834},{"source":"Elieser Hernandez","target":"Trevor Cahill","distance":1.8118},{"source":"Asher Wojciechowski","target":"Trevor Cahill","distance":1.8133},{"source":"Jeff Hoffman","target":"Trevor Cahill","distance":1.8953},{"source":"Mike Foltynewicz","target":"Trevor Cahill","distance":1.9291},{"source":"Domingo German","target":"Trevor Cahill","distance":1.9891},{"source":"Tyler Beede","target":"Trevor Cahill","distance":2.0025},{"source":"Adam Plutko","target":"Trevor Cahill","distance":2.0175},{"source":"Vince Velasquez","target":"Trevor Cahill","distance":2.0194},{"source":"Mike Montgomery","target":"Trevor Cahill","distance":2.0255},{"source":"Gabriel Ynoa","target":"Trevor Cahill","distance":2.0609},{"source":"Reynaldo Lopez","target":"Trevor Cahill","distance":2.0632},{"source":"Drew Smyly","target":"Trevor Cahill","distance":2.0681},{"source":"Peter Lambert","target":"Trevor Cahill","distance":2.1044},{"source":"Trevor Williams","target":"Trevor Cahill","distance":2.1081},{"source":"Matt Strahm","target":"Trevor Cahill","distance":2.1424},{"source":"Ariel Jurado","target":"Trevor Cahill","distance":2.1542},{"source":"Caleb Smith","target":"Trevor Cahill","distance":2.1612},{"source":"Alex Young","target":"Trevor Cahill","distance":2.1708},{"source":"Dario Agrazal","target":"Trevor Cahill","distance":2.2457},{"source":"Tyler Mahle","target":"Trevor Cahill","distance":2.3016},{"source":"Michael Wacha","target":"Trevor Cahill","distance":2.3084},{"source":"Jakob Junis","target":"Trevor Cahill","distance":2.3097},{"source":"Matt Harvey","target":"Trevor Cahill","distance":2.388},{"source":"Rick Porcello","target":"Trevor Cahill","distance":2.3911},{"source":"Dylan Bundy","target":"Trevor Cahill","distance":2.3925},{"source":"Zach Eflin","target":"Trevor Cahill","distance":2.4054},{"source":"Zach Plesac","target":"Trevor Cahill","distance":2.4536},{"source":"Steven Matz","target":"Trevor Cahill","distance":2.461},{"source":"Tanner Roark","target":"Trevor Cahill","distance":2.493},{"source":"Anthony DeSclafani","target":"Trevor Cahill","distance":2.5047},{"source":"Danny Duffy","target":"Trevor Cahill","distance":2.5328},{"source":"Jordan Lyles","target":"Trevor Cahill","distance":2.5406},{"source":"Drew Pomeranz","target":"Trevor Cahill","distance":2.5924},{"source":"Merrill Kelly","target":"Trevor Cahill","distance":2.5948},{"source":"Mike Fiers","target":"Trevor Cahill","distance":2.6229},{"source":"Cal Quantrill","target":"Trevor Cahill","distance":2.6229},{"source":"Chase Anderson","target":"Trevor Cahill","distance":2.6241},{"source":"Jake Arrieta","target":"Trevor Cahill","distance":2.6587},{"source":"Andrew Heaney","target":"Trevor Cahill","distance":2.6635},{"source":"Daniel Norris","target":"Trevor Cahill","distance":2.6814},{"source":"Jordan Zimmermann","target":"Trevor Cahill","distance":2.7178},{"source":"Trent Thornton","target":"Trevor Cahill","distance":2.7345},{"source":"Jeff Samardzija","target":"Trevor Cahill","distance":2.7431},{"source":"Brad Peacock","target":"Trevor Cahill","distance":2.7696},{"source":"Chris Bassitt","target":"Trevor Cahill","distance":2.7762},{"source":"Martin Perez","target":"Trevor Cahill","distance":2.7881},{"source":"Dylan Cease","target":"Trevor Cahill","distance":2.7936},{"source":"Jon Lester","target":"Trevor Cahill","distance":2.8139},{"source":"Kevin Gausman","target":"Trevor Cahill","distance":2.8289},{"source":"Nathan Eovaldi","target":"Trevor Cahill","distance":2.8317},{"source":"Dallas Keuchel","target":"Trevor Cahill","distance":2.8441},{"source":"Chris Archer","target":"Trevor Cahill","distance":2.8753},{"source":"Ivan Nova","target":"Trevor Cahill","distance":2.8793},{"source":"Shaun Anderson","target":"Trevor Cahill","distance":2.899},{"source":"Mike Minor","target":"Trevor Cahill","distance":2.9025},{"source":"Andrew Cashner","target":"Trevor Cahill","distance":2.9167},{"source":"Masahiro Tanaka","target":"Trevor Cahill","distance":2.9358},{"source":"Matthew Boyd","target":"Trevor Cahill","distance":2.9401},{"source":"Wade Miley","target":"Trevor Cahill","distance":2.9423},{"source":"Erick Fedde","target":"Trevor Cahill","distance":2.9485},{"source":"Adrian Houser","target":"Trevor Cahill","distance":2.9566},{"source":"Kyle Gibson","target":"Trevor Cahill","distance":2.9681},{"source":"Jacob Waguespack","target":"Trevor Cahill","distance":2.9744},{"source":"Mike Leake","target":"Trevor Cahill","distance":2.9751},{"source":"Trevor Richards","target":"Trevor Cahill","distance":2.9808},{"source":"John Means","target":"Trevor Cahill","distance":2.9815},{"source":"Joey Lucchesi","target":"Trevor Cahill","distance":2.9844},{"source":"Yonny Chirinos","target":"Trevor Cahill","distance":2.9986},{"source":"Anibal Sanchez","target":"Trevor Cahill","distance":3.0251},{"source":"Griffin Canning","target":"Trevor Cahill","distance":3.0354},{"source":"Eric Lauer","target":"Trevor Cahill","distance":3.0365},{"source":"German Marquez","target":"Trevor Cahill","distance":3.038},{"source":"Jose Urena","target":"Trevor Cahill","distance":3.062},{"source":"Clayton Kershaw","target":"Trevor Cahill","distance":3.1015},{"source":"Yu Darvish","target":"Trevor Cahill","distance":3.1239},{"source":"Homer Bailey","target":"Trevor Cahill","distance":3.1287},{"source":"Chris Paddack","target":"Trevor Cahill","distance":3.1312},{"source":"Rich Hill","target":"Trevor Cahill","distance":3.1314},{"source":"Jason Vargas","target":"Trevor Cahill","distance":3.1456},{"source":"Antonio Senzatela","target":"Trevor Cahill","distance":3.1484},{"source":"Adam Wainwright","target":"Trevor Cahill","distance":3.1567},{"source":"Michael Pineda","target":"Trevor Cahill","distance":3.1586},{"source":"Trevor Bauer","target":"Trevor Cahill","distance":3.1761},{"source":"Kenta Maeda","target":"Trevor Cahill","distance":3.1793},{"source":"Carlos Carrasco","target":"Trevor Cahill","distance":3.1816},{"source":"Pablo Lopez","target":"Trevor Cahill","distance":3.1907},{"source":"Steven Brault","target":"Trevor Cahill","distance":3.2185},{"source":"Zach Davies","target":"Trevor Cahill","distance":3.254},{"source":"Jon Gray","target":"Trevor Cahill","distance":3.2697},{"source":"Madison Bumgarner","target":"Trevor Cahill","distance":3.2968},{"source":"Jose Berrios","target":"Trevor Cahill","distance":3.3127},{"source":"Chi Chi Gonzalez","target":"Trevor Cahill","distance":3.3269},{"source":"Max Fried","target":"Trevor Cahill","distance":3.3425},{"source":"Miles Mikolas","target":"Trevor Cahill","distance":3.3543},{"source":"Jose Quintana","target":"Trevor Cahill","distance":3.3842},{"source":"James Paxton","target":"Trevor Cahill","distance":3.3935},{"source":"Ross Stripling","target":"Trevor Cahill","distance":3.3989},{"source":"Jordan Yamamoto","target":"Trevor Cahill","distance":3.4009},{"source":"Aaron Sanchez","target":"Trevor Cahill","distance":3.403},{"source":"Sandy Alcantara","target":"Trevor Cahill","distance":3.4136},{"source":"Joe Musgrove","target":"Trevor Cahill","distance":3.4422},{"source":"Cole Hamels","target":"Trevor Cahill","distance":3.4543},{"source":"Aaron Nola","target":"Trevor Cahill","distance":3.4598},{"source":"Marco Gonzales","target":"Trevor Cahill","distance":3.4628},{"source":"Tyler Skaggs","target":"Trevor Cahill","distance":3.4688},{"source":"David Price","target":"Trevor Cahill","distance":3.4694},{"source":"Eduardo Rodriguez","target":"Trevor Cahill","distance":3.5043},{"source":"Noah Syndergaard","target":"Trevor Cahill","distance":3.528},{"source":"Julio Teheran","target":"Trevor Cahill","distance":3.5762},{"source":"Dakota Hudson","target":"Trevor Cahill","distance":3.5851},{"source":"Zack Wheeler","target":"Trevor Cahill","distance":3.6359},{"source":"Gio Gonzalez","target":"Trevor Cahill","distance":3.6377},{"source":"Jack Flaherty","target":"Trevor Cahill","distance":3.6485},{"source":"Marcus Stroman","target":"Trevor Cahill","distance":3.6629},{"source":"Brett Anderson","target":"Trevor Cahill","distance":3.7203},{"source":"Patrick Corbin","target":"Trevor Cahill","distance":3.7296},{"source":"Lucas Giolito","target":"Trevor Cahill","distance":3.7887},{"source":"Shane Bieber","target":"Trevor Cahill","distance":3.8187},{"source":"Spencer Turnbull","target":"Trevor Cahill","distance":3.8659},{"source":"Robbie Ray","target":"Trevor Cahill","distance":3.8781},{"source":"Jake Odorizzi","target":"Trevor Cahill","distance":3.8935},{"source":"Luis Castillo","target":"Trevor Cahill","distance":3.9022},{"source":"Brad Keller","target":"Trevor Cahill","distance":3.9066},{"source":"Kyle Hendricks","target":"Trevor Cahill","distance":3.9179},{"source":"Stephen Strasburg","target":"Trevor Cahill","distance":3.9386},{"source":"Justin Verlander","target":"Trevor Cahill","distance":4.015},{"source":"Dinelson Lamet","target":"Trevor Cahill","distance":4.017},{"source":"Lance Lynn","target":"Trevor Cahill","distance":4.0683},{"source":"Sonny Gray","target":"Trevor Cahill","distance":4.1055},{"source":"Blake Snell","target":"Trevor Cahill","distance":4.125},{"source":"Mike Soroka","target":"Trevor Cahill","distance":4.1414},{"source":"Walker Buehler","target":"Trevor Cahill","distance":4.1753},{"source":"Brandon Woodruff","target":"Trevor Cahill","distance":4.1789},{"source":"Luke Weaver","target":"Trevor Cahill","distance":4.1802},{"source":"Chris Sale","target":"Trevor Cahill","distance":4.218},{"source":"Aaron Civale","target":"Trevor Cahill","distance":4.2216},{"source":"Zack Greinke","target":"Trevor Cahill","distance":4.2592},{"source":"Ryan Yarbrough","target":"Trevor Cahill","distance":4.264},{"source":"Frankie Montas","target":"Trevor Cahill","distance":4.267},{"source":"Zac Gallen","target":"Trevor Cahill","distance":4.2825},{"source":"Hyun-Jin Ryu","target":"Trevor Cahill","distance":4.4507},{"source":"Jacob deGrom","target":"Trevor Cahill","distance":4.5305},{"source":"Charlie Morton","target":"Trevor Cahill","distance":4.5558},{"source":"Mike Clevinger","target":"Trevor Cahill","distance":4.7836},{"source":"Gerrit Cole","target":"Trevor Cahill","distance":4.787},{"source":"Max Scherzer","target":"Trevor Cahill","distance":4.8909},{"source":"Tyler Glasnow","target":"Trevor Cahill","distance":4.9058}]
